energy_analysis_toolbox/__init__.py
energy_analysis_toolbox/constants.py
energy_analysis_toolbox/keywords.py
energy_analysis_toolbox/pandas.py
energy_analysis_toolbox/energy/__init__.py
energy_analysis_toolbox/energy/resample.py
energy_analysis_toolbox/errors/__init__.py
energy_analysis_toolbox/errors/base.py
energy_analysis_toolbox/errors/invalid_timeseries.py
energy_analysis_toolbox/errors/resampling.py
energy_analysis_toolbox/power/__init__.py
energy_analysis_toolbox/power/basics.py
energy_analysis_toolbox/power/resample.py
energy_analysis_toolbox/power/overconsumption/__init__.py
energy_analysis_toolbox/power/overconsumption/find.py
energy_analysis_toolbox/power/overconsumption/select.py
energy_analysis_toolbox/power/overconsumption/transform.py
energy_analysis_toolbox/synthetic/__init__.py
energy_analysis_toolbox/synthetic/thermosensitive_consumption.py
energy_analysis_toolbox/tests/__init__.py
energy_analysis_toolbox/tests/main.py
energy_analysis_toolbox/tests/test_energy_resample.py
energy_analysis_toolbox/tests/test_exists.py
energy_analysis_toolbox/tests/test_pandas.py
energy_analysis_toolbox/tests/test_power_basics.py
energy_analysis_toolbox/tests/test_power_overconsumption_find.py
energy_analysis_toolbox/tests/test_power_overconsumption_select.py
energy_analysis_toolbox/tests/test_power_overconsumption_transform.py
energy_analysis_toolbox/tests/test_power_resample.py
energy_analysis_toolbox/tests/test_synthetic.py
energy_analysis_toolbox/tests/test_thermosensitivity.py
energy_analysis_toolbox/tests/test_timeseries_create_from_intervals.py
energy_analysis_toolbox/tests/test_timeseries_extract_features_basics.py
energy_analysis_toolbox/tests/test_timeseries_resample_conservative.py
energy_analysis_toolbox/tests/test_timeseries_resample_facade.py
energy_analysis_toolbox/tests/test_timeseries_resample_index_transformation.py
energy_analysis_toolbox/tests/test_timeseries_resample_interpolate.py
energy_analysis_toolbox/tests/test_weather_degree_days.py
energy_analysis_toolbox-0.1.4.dist-info/LICENSE
energy_analysis_toolbox-0.1.4.dist-info/METADATA
energy_analysis_toolbox-0.1.4.dist-info/WHEEL
energy_analysis_toolbox-0.1.4.dist-info/top_level.txt
energy_analysis_toolbox-0.1.4.dist-info/RECORD
