Metadata-Version: 2.1
Name: energy_analysis_toolbox
Version: 0.1.4
Summary: A set of tools to manipulate and transform power, energy, and related timeseries data.
Author-email: energy_analysis_toolbox contributors <research@ecoco2.com>
License: MIT
Project-URL: Homepage, https://github.com/Eco-CO2/energy_analysis_toolbox
Project-URL: Bug Tracker, https://github.com/Eco-CO2/energy_analysis_toolbox/issues
Keywords: profile
Classifier: Programming Language :: Python :: 3
Requires-Python: >=3.8
License-File: LICENSE
Requires-Dist: pandas >=2.2.2
Requires-Dist: numpy >=1.26.0
Requires-Dist: scipy >=1.13.0
Requires-Dist: statsmodels >=0.13.0
Provides-Extra: all
Requires-Dist: energy-analysis-toolbox[doc,test] ; extra == 'all'
Provides-Extra: doc
Requires-Dist: energy-analysis-toolbox[examples] ; extra == 'doc'
Requires-Dist: sphinx ; extra == 'doc'
Requires-Dist: pydata-sphinx-theme ; extra == 'doc'
Requires-Dist: sphinx-gallery ; extra == 'doc'
Requires-Dist: sphinx-design ; extra == 'doc'
Requires-Dist: nbsphinx ; extra == 'doc'
Provides-Extra: test
Requires-Dist: pytest ; extra == 'test'
Requires-Dist: pytest-cov ; extra == 'test'
